gpuwatcher/__init__.py
gpuwatcher/gpuwatcher.py
gpuwatcher/utils.py
gpuwatcher-0.0.10.dist-info/METADATA
gpuwatcher-0.0.10.dist-info/WHEEL
gpuwatcher-0.0.10.dist-info/entry_points.txt
gpuwatcher-0.0.10.dist-info/top_level.txt
gpuwatcher-0.0.10.dist-info/zip-safe
gpuwatcher-0.0.10.dist-info/RECORD
