Metadata-Version: 2.1
Name: gpuwatcher
Version: 0.0.10
Summary: Monitor the memory usage and notify
Home-page: UNKNOWN
Author: Kun song
Author-email: songkun666@outlook.com
License: MIT
Keywords: gpu,watcher,notify,webhook,feishu
Platform: UNKNOWN
Requires-Dist: psutil
Requires-Dist: nvidia-ml-py3
